maquina de estados V3.0_Quartus/antirrebote.v
module antirrebote (
    input clk,
    input boton_in,
    output reg boton_out
);
    reg [2:0] contador = 0;
    reg estado_actual = 1'b0;

    
    initial begin
        boton_out = 1'b0;
    end

    always @(posedge clk) begin
        if (boton_in != estado_actual) begin
            contador <= contador + 1'b1;
            if (contador == 3'b111) begin
                estado_actual <= boton_in;
                boton_out     <= boton_in;
                contador      <= 0;
            end
        end else begin
            contador <= 0;
        end
    end
endmodule

Lab03/src/deco_7seg.v
module deco_7seg(
    input      [3:0] num, // Entrada: la magnitud de tu número (0 al 9)
    output reg [6:0] seg_out // Salida: los 7 segmentos [g, f, e, d, c, b, a]
);

    always @(*) begin
        
        case(num)
            // Formato: 7'b g_f_e_d_c_b_a
            4'd0: seg_out = 7'b1000000; 
            4'd1: seg_out = 7'b1111001; 
            4'd2: seg_out = 7'b0100100; 
            4'd3: seg_out = 7'b0110000; 
            4'd4: seg_out = 7'b0011001; 
            4'd5: seg_out = 7'b0010010; 
            4'd6: seg_out = 7'b0000010; 
            4'd7: seg_out = 7'b1111000; 
            4'd8: seg_out = 7'b0000000; 
            4'd9: seg_out = 7'b0010000; 
            
            
            default: seg_out = 7'b1111111; 
        endcase
    end

endmodule

Lab03/src/double.v
module double (
    input  [5:0] bin,       // Tu entrada 'pp' de 6 bits
    output reg [3:0] decenas,
    output reg [3:0] unidades
);

    reg [13:0] caja;        // Nuestra caja gigante de 14 espacios

    always @(*) begin
        caja = {4'd0, 4'd0, bin};

        // --- DESPLAZAMIENTO 1 ---
        if (caja[9:6] >= 5) caja[9:6] = caja[9:6] + 3;       // Revisa las unidades
        if (caja[13:10] >= 5) caja[13:10] = caja[13:10] + 3; // Revisa las decenas
        caja = caja << 1;                                    // Corre toda la caja 1 bit a la izquierda

        // --- DESPLAZAMIENTO 2 ---
        if (caja[9:6] >= 5) caja[9:6] = caja[9:6] + 3;
        if (caja[13:10] >= 5) caja[13:10] = caja[13:10] + 3;
        caja = caja << 1;

        // --- DESPLAZAMIENTO 3 ---
        if (caja[9:6] >= 5) caja[9:6] = caja[9:6] + 3;
        if (caja[13:10] >= 5) caja[13:10] = caja[13:10] + 3;
        caja = caja << 1;

        // --- DESPLAZAMIENTO 4 ---
        if (caja[9:6] >= 5) caja[9:6] = caja[9:6] + 3;
        if (caja[13:10] >= 5) caja[13:10] = caja[13:10] + 3;
        caja = caja << 1;

        // --- DESPLAZAMIENTO 5 ---
        if (caja[9:6] >= 5) caja[9:6] = caja[9:6] + 3;
        if (caja[13:10] >= 5) caja[13:10] = caja[13:10] + 3;
        caja = caja << 1;

        // --- DESPLAZAMIENTO 6 ---
        if (caja[9:6] >= 5) caja[9:6] = caja[9:6] + 3;
        if (caja[13:10] >= 5) caja[13:10] = caja[13:10] + 3;
        caja = caja << 1;

        decenas  = caja[13:10];
        unidades = caja[9:6];
    end

endmodule

Lab03/src/multiplicador.v
`timescale 1s/1s
`include "double.v"
`include "deco_7seg.v"
`include "antirrebote.v"



module multiplicador (
    input        clk,
    input        rst,     
    input        init,    
    input  [2:0] md,      
    input  [2:0] mr,      
    output reg [5:0] pp,  
    output reg       done,
    output [6:0]  display_uni,
    output [6:0]  display_des
);

    //----------------------------------------------------------
    // Estados
    //----------------------------------------------------------
    parameter START = 3'd0;
    parameter CHECK = 3'd1;
    parameter ADD   = 3'd2;
    parameter SHIFT = 3'd3;
    parameter END   = 3'd4;

    reg [2:0] estado;
    reg [2:0] siguiente;

    wire [3:0] uni;
    wire [3:0] des;

    wire rst_anti;
    wire init_anti;

    
    reg reset;
    reg sh;
    reg add;


    reg [5:0] a;
    reg [2:0] b;


    wire lsb_b;
    wire z;

    assign lsb_b = b[0];
    assign z     = (b[2:1] == 2'b00);  // B sera 0 despues del shift

    // MAQUINA DE ESTADOS

    always @(posedge clk or posedge rst) begin
        if (rst)
            estado <= START;
        else
            estado <= siguiente;
    end




    // Logica de siguiente estado
    always @(*) begin
        case (estado)
            START: begin
                if (init) siguiente = CHECK;
                else      siguiente = START;
            end

            CHECK: begin
                if (lsb_b) siguiente = ADD;
                else       siguiente = SHIFT;
            end

            ADD: begin
                siguiente = SHIFT;
            end

            SHIFT: begin
                if (z) siguiente = END;
                else   siguiente = CHECK;
            end

            END: begin
                siguiente = START;
            end

            default: begin
                siguiente = START;
            end
        endcase
    end


    always @(*) begin
        done  = 1'b0;
        reset = 1'b0;
        sh    = 1'b0;
        add   = 1'b0;
        case (estado)
            START: reset = 1'b1;
            CHECK: ;
            ADD:   add   = 1'b1;
            SHIFT: sh    = 1'b1;
            END:   done  = 1'b1;
            default: ;
        endcase
    end


    // DATAPACTH

    always @(posedge clk) begin
        if (reset) begin
            a  <= {3'b000, md};
            b  <= mr;
            pp <= 6'b000000;
        end
        else if (add) begin
            pp <= pp + a;
        end
        else if (sh) begin
            a <= a << 1;
            b <= b >> 1;
        end
    end

double  mi_conversor (
        .bin      (pp), 
        .decenas  (des),
        .unidades (uni)
    );

deco_7seg unid (
        .num       (uni),
        .seg_out   (display_uni)
);


deco_7seg desce (
        .num       (des),
        .seg_out   (display_des)
);

antirrebote anti_1 (
        .clk      (clk),
        .boton_in   (rst),
        .boton_out  (rst_anti)
);


antirrebote anti_2 (
        .clk        (clk),
        .boton_in   (init),
        .boton_out  (init_anti)
);



endmodule

Lab03/src/multiplicadortb.v
`include "multiplicador.v"
`timescale 1s/1s

module multiplicador_tb();
    reg        clk_tb;
    reg        rst_tb;     
    reg        init_tb;    
    reg  [2:0] md_tb;      
    reg  [2:0] mr_tb;      
    wire [5:0] pp_tb;  
    wire       done_tb;
    wire [6:0] display_uni_tb;
    wire [6:0] display_des_tb;

    // Instancia del Top Level
    multiplicador uut (
        .clk         (clk_tb),
        .rst         (rst_tb),
        .init        (init_tb),
        .md          (md_tb),
        .mr          (mr_tb),
        .pp          (pp_tb),
        .done        (done_tb),
        .display_uni (display_uni_tb),
        .display_des (display_des_tb)
    );

    integer i, j;

    // Generador de Reloj
    always #1 clk_tb = ~clk_tb; 

    initial begin
        $dumpfile("simulacion_tb.vcd");
        $dumpvars(-1, uut);

        // Estado inicial
        clk_tb  = 0;
        rst_tb  = 0;
        init_tb = 0;
        mr_tb   = 0;
        md_tb   = 0;

        #2;
        // Pulso rápido de Reset (1 ciclo)
        rst_tb = 1;
        #2;
        rst_tb = 0;
        #2;

        // Bucle para probar de 0x0 a 7x7
        for (i = 0; i < 8; i = i + 1) begin        
            for (j = 0; j < 8; j = j + 1) begin    

                mr_tb = i;
                md_tb = j;

                // Pulso de inicio directo de 1 ciclo
                @(posedge clk_tb);
                init_tb = 1;
                @(posedge clk_tb);
                init_tb = 0; 

                // Esperar a que finalice la multiplicación
                wait(done_tb == 1'b1);
                @(posedge clk_tb);

                if (pp_tb !== (i * j)) begin
                    $display("[ERROR] %d x %d = %d | Esperado: %d", i, j, pp_tb, (i * j));
                end else begin
                    $display("[OK]    %d x %d = %d", i, j, pp_tb);
                end
            end
        end

        #10;
        $display("--- SIMULACION FINALIZADA EXITOSAMENTE ---");
        $finish;
    end

endmodule

Lab03/build/simulacion_tb.vcd
$date
	Thu Sep 24 17:16:46 2026
$end
$version
	Icarus Verilog
$end
$timescale
	1s
$end
$scope module multiplicador_tb $end
$scope module uut $end
$var wire 1 ! clk $end
$var wire 1 " init $end
$var wire 3 # md [2:0] $end
$var wire 3 $ mr [2:0] $end
$var wire 1 % rst $end
$var wire 1 & z $end
$var wire 4 ' uni [3:0] $end
$var wire 1 ( rst_anti $end
$var wire 1 ) lsb_b $end
$var wire 1 * init_anti $end
$var wire 7 + display_uni [6:0] $end
$var wire 7 , display_des [6:0] $end
$var wire 4 - des [3:0] $end
$var reg 6 . a [5:0] $end
$var reg 1 / add $end
$var reg 3 0 b [2:0] $end
$var reg 1 1 done $end
$var reg 3 2 estado [2:0] $end
$var reg 6 3 pp [5:0] $end
$var reg 1 4 reset $end
$var reg 1 5 sh $end
$var reg 3 6 siguiente [2:0] $end
$scope module anti_1 $end
$var wire 1 % boton_in $end
$var wire 1 ! clk $end
$var reg 1 ( boton_out $end
$var reg 3 7 contador [2:0] $end
$var reg 1 8 estado_actual $end
$upscope $end
$scope module anti_2 $end
$var wire 1 " boton_in $end
$var wire 1 ! clk $end
$var reg 1 * boton_out $end
$var reg 3 9 contador [2:0] $end
$var reg 1 : estado_actual $end
$upscope $end
$scope module desce $end
$var wire 4 ; num [3:0] $end
$var reg 7 < seg_out [6:0] $end
$upscope $end
$scope module mi_conversor $end
$var wire 6 = bin [5:0] $end
$var reg 14 > caja [13:0] $end
$var reg 4 ? decenas [3:0] $end
$var reg 4 @ unidades [3:0] $end
$upscope $end
$scope module unid $end
$var wire 4 A num [3:0] $end
$var reg 7 B seg_out [6:0] $end
$upscope $end
$upscope $end
$upscope $end
$enddefinitions $end
#0
$dumpvars
bx B
bx A
bx @
bx ?
bx >
bx =
bx <
bx ;
0:
b0 9
08
b0 7
b0 6
x5
x4
bx 3
bx 2
x1
bx 0
x/
bx .
bx -
bx ,
bx +
0*
x)
0(
bx '
x&
0%
b0 $
b0 #
0"
0!
$end
#1
0/
05
14
01
b0 2
1!
#2
0!
1%
#3
b1000000 +
b1000000 B
b1000000 ,
b1000000 <
b0 '
b0 @
b0 A
b0 -
b0 ;
b0 ?
b0 >
0)
1&
b0 3
b0 =
b0 0
b0 .
b1 7
1!
#4
0!
0%
#5
b0 7
1!
#6
0!
#7
b1 9
b1 6
1"
1!
#8
0!
#9
04
b10 9
b1 2
b11 6
0"
1!
#10
0!
#11
15
b100 6
b0 9
b11 2
1!
#12
0!
#13
11
05
b0 6
b100 2
1!
#14
0!
#15
14
01
b0 2
b1 #
1!
#16
0!
#17
b1 .
b1 6
1"
1!
#18
0!
#19
04
b1 2
b11 6
0"
1!
#20
0!
#21
15
b100 6
b11 2
1!
#22
0!
#23
11
05
b0 6
b10 .
b100 2
1!
#24
0!
#25
14
01
b0 2
b10 #
1!
#26
0!
#27
b1 6
1"
1!
#28
0!
#29
04
b1 2
b11 6
0"
1!
#30
0!
#31
15
b100 6
b11 2
1!
#32
0!
#33
11
05
b0 6
b100 .
b100 2
1!
#34
0!
#35
14
01
b0 2
b11 #
1!
#36
0!
#37
b11 .
b1 6
1"
1!
#38
0!
#39
04
b1 2
b11 6
0"
1!
#40
0!
#41
15
b100 6
b11 2
1!
#42
0!
#43
11
05
b0 6
b110 .
b100 2
1!
#44
0!
#45
14
01
b0 2
b100 #
1!
#46
0!
#47
b100 .
b1 6
1"
1!
#48
0!
#49
04
b1 2
b11 6
0"
1!
#50
0!
#51
15
b100 6
b11 2
1!
#52
0!
#53
11
05
b0 6
b1000 .
b100 2
1!
#54
0!
#55
14
01
b0 2
b101 #
1!
#56
0!
#57
b101 .
b1 6
1"
1!
#58
0!
#59
04
b1 2
b11 6
0"
1!
#60
0!
#61
15
b100 6
b11 2
1!
#62
0!
#63
11
05
b0 6
b1010 .
b100 2
1!
#64
0!
#65
14
01
b0 2
b110 #
1!
#66
0!
#67
b110 .
b1 6
1"
1!
#68
0!
#69
04
b1 2
b11 6
0"
1!
#70
0!
#71
15
b100 6
b11 2
1!
#72
0!
#73
11
05
b0 6
b1100 .
b100 2
1!
#74
0!
#75
14
01
b0 2
b111 #
1!
#76
0!
#77
b111 .
b1 6
1"
1!
#78
0!
#79
04
b1 2
b11 6
0"
1!
#80
0!
#81
15
b100 6
b11 2
1!
#82
0!
#83
11
05
b0 6
b1110 .
b100 2
1!
#84
0!
#85
14
01
b0 2
b0 #
b1 $
1!
#86
0!
#87
1)
b1 0
b0 .
b1 6
1"
1!
#88
0!
#89
04
b1 2
b10 6
0"
1!
#90
0!
#91
1/
b11 6
b10 2
1!
#92
0!
#93
15
0/
b100 6
b11 2
1!
#94
0!
#95
0)
11
05
b0 6
b0 0
b100 2
1!
#96
0!
#97
14
01
b0 2
b1 #
1!
#98
0!
#99
1)
b1 0
b1 .
b1 6
1"
1!
#100
0!
#101
04
b1 2
b10 6
0"
1!
#102
0!
#103
1/
b11 6
b10 2
1!
#104
0!
#105
b1111001 +
b1111001 B
b1 '
b1 @
b1 A
b1000000 >
15
0/
b100 6
b1 3
b1 =
b11 2
1!
#106
0!
#107
0)
11
05
b0 6
b0 0
b10 .
b100 2
1!
#108
0!
#109
14
01
b0 2
b10 #
1!
#110
0!
#111
b1000000 +
b1000000 B
b0 '
b0 @
b0 A
b0 >
1)
b0 3
b0 =
b1 0
b1 6
1"
1!
#112
0!
#113
04
b1 2
b10 6
0"
1!
#114
0!
#115
1/
b11 6
b10 2
1!
#116
0!
#117
b100100 +
b100100 B
b10 '
b10 @
b10 A
b10000000 >
15
0/
b100 6
b10 3
b10 =
b11 2
1!
#118
0!
#119
0)
11
05
b0 6
b0 0
b100 .
b100 2
1!
#120
0!
#121
14
01
b0 2
b11 #
1!
#122
0!
#123
b1000000 +
b1000000 B
b0 '
b0 @
b0 A
b0 >
1)
b0 3
b0 =
b1 0
b11 .
b1 6
1"
1!
#124
0!
#125
04
b1 2
b10 6
0"
1!
#126
0!
#127
1/
b11 6
b10 2
1!
#128
0!
#129
b110000 +
b110000 B
b11 '
b11 @
b11 A
b11000000 >
15
0/
b100 6
b11 3
b11 =
b11 2
1!
#130
0!
#131
0)
11
05
b0 6
b0 0
b110 .
b100 2
1!
#132
0!
#133
14
01
b0 2
b100 #
1!
#134
0!
#135
b1000000 +
b1000000 B
b0 '
b0 @
b0 A
b0 >
1)
b0 3
b0 =
b1 0
b100 .
b1 6
1"
1!
#136
0!
#137
04
b1 2
b10 6
0"
1!
#138
0!
#139
1/
b11 6
b10 2
1!
#140
0!
#141
b11001 +
b11001 B
b100 '
b100 @
b100 A
b100000000 >
15
0/
b100 6
b100 3
b100 =
b11 2
1!
#142
0!
#143
0)
11
05
b0 6
b0 0
b1000 .
b100 2
1!
#144
0!
#145
14
01
b0 2
b101 #
1!
#146
0!
#147
b1000000 +
b1000000 B
b0 '
b0 @
b0 A
b0 >
1)
b0 3
b0 =
b1 0
b101 .
b1 6
1"
1!
#148
0!
#149
04
b1 2
b10 6
0"
1!
#150
0!
#151
1/
b11 6
b10 2
1!
#152
0!
#153
b10010 +
b10010 B
b101 '
b101 @
b101 A
b101000000 >
15
0/
b100 6
b101 3
b101 =
b11 2
1!
#154
0!
#155
0)
11
05
b0 6
b0 0
b1010 .
b100 2
1!
#156
0!
#157
14
01
b0 2
b110 #
1!
#158
0!
#159
b1000000 +
b1000000 B
b0 '
b0 @
b0 A
b0 >
1)
b0 3
b0 =
b1 0
b110 .
b1 6
1"
1!
#160
0!
#161
04
b1 2
b10 6
0"
1!
#162
0!
#163
1/
b11 6
b10 2
1!
#164
0!
#165
b10 +
b10 B
b110 '
b110 @
b110 A
b110000000 >
15
0/
b100 6
b110 3
b110 =
b11 2
1!
#166
0!
#167
0)
11
05
b0 6
b0 0
b1100 .
b100 2
1!
#168
0!
#169
14
01
b0 2
b111 #
1!
#170
0!
#171
b1000000 +
b1000000 B
b0 '
b0 @
b0 A
b0 >
1)
b0 3
b0 =
b1 0
b111 .
b1 6
1"
1!
#172
0!
#173
04
b1 2
b10 6
0"
1!
#174
0!
#175
1/
b11 6
b10 2
1!
#176
0!
#177
b1111000 +
b1111000 B
b111 '
b111 @
b111 A
b111000000 >
15
0/
b100 6
b111 3
b111 =
b11 2
1!
#178
0!
#179
0)
11
05
b0 6
b0 0
b1110 .
b100 2
1!
#180
0!
#181
14
01
b0 2
b0 #
b10 $
1!
#182
0!
#183
b1000000 +
b1000000 B
b0 '
b0 @
b0 A
b0 >
0&
b0 3
b0 =
b10 0
b0 .
b1 6
1"
1!
#184
0!
#185
04
b1 2
b11 6
0"
1!
#186
0!
#187
15
b1 6
b11 2
1!
#188
0!
#189
1)
1&
05
b10 6
b1 0
b1 2
1!
#190
0!
#191
1/
b11 6
b10 2
1!
#192
0!
#193
15
0/
b100 6
b11 2
1!
#194
0!
#195
0)
11
05
b0 6
b0 0
b100 2
1!
#196
0!
#197
14
01
b0 2
b1 #
1!
#198
0!
#199
0&
b10 0
b1 .
b1 6
1"
1!
#200
0!
#201
04
b1 2
b11 6
0"
1!
#202
0!
#203
15
b1 6
b11 2
1!
#204
0!
#205
1)
1&
05
b10 6
b1 0
b10 .
b1 2
1!
#206
0!
#207
1/
b11 6
b10 2
1!
#208
0!
#209
b100100 +
b100100 B
b10 '
b10 @
b10 A
b10000000 >
15
0/
b100 6
b10 3
b10 =
b11 2
1!
#210
0!
#211
0)
11
05
b0 6
b0 0
b100 .
b100 2
1!
#212
0!
#213
14
01
b0 2
b10 #
1!
#214
0!
#215
b1000000 +
b1000000 B
b0 '
b0 @
b0 A
b0 >
0&
b0 3
b0 =
b10 0
b10 .
b1 6
1"
1!
#216
0!
#217
04
b1 2
b11 6
0"
1!
#218
0!
#219
15
b1 6
b11 2
1!
#220
0!
#221
1)
1&
05
b10 6
b1 0
b100 .
b1 2
1!
#222
0!
#223
1/
b11 6
b10 2
1!
#224
0!
#225
b11001 +
b11001 B
b100 '
b100 @
b100 A
b100000000 >
15
0/
b100 6
b100 3
b100 =
b11 2
1!
#226
0!
#227
0)
11
05
b0 6
b0 0
b1000 .
b100 2
1!
#228
0!
#229
14
01
b0 2
b11 #
1!
#230
0!
#231
b1000000 +
b1000000 B
b0 '
b0 @
b0 A
b0 >
0&
b0 3
b0 =
b10 0
b11 .
b1 6
1"
1!
#232
0!
#233
04
b1 2
b11 6
0"
1!
#234
0!
#235
15
b1 6
b11 2
1!
#236
0!
#237
1)
1&
05
b10 6
b1 0
b110 .
b1 2
1!
#238
0!
#239
1/
b11 6
b10 2
1!
#240
0!
#241
b10 +
b10 B
b110 '
b110 @
b110 A
b110000000 >
15
0/
b100 6
b110 3
b110 =
b11 2
1!
#242
0!
#243
0)
11
05
b0 6
b0 0
b1100 .
b100 2
1!
#244
0!
#245
14
01
b0 2
b100 #
1!
#246
0!
#247
b1000000 +
b1000000 B
b0 '
b0 @
b0 A
b0 >
0&
b0 3
b0 =
b10 0
b100 .
b1 6
1"
1!
#248
0!
#249
04
b1 2
b11 6
0"
1!
#250
0!
#251
15
b1 6
b11 2
1!
#252
0!
#253
1)
1&
05
b10 6
b1 0
b1000 .
b1 2
1!
#254
0!
#255
1/
b11 6
b10 2
1!
#256
0!
#257
b0 +
b0 B
b1000 '
b1000 @
b1000 A
b1000000000 >
15
0/
b100 6
b1000 3
b1000 =
b11 2
1!
#258
0!
#259
0)
11
05
b0 6
b0 0
b10000 .
b100 2
1!
#260
0!
#261
14
01
b0 2
b101 #
1!
#262
0!
#263
b1000000 +
b1000000 B
b0 '
b0 @
b0 A
b0 >
0&
b0 3
b0 =
b10 0
b101 .
b1 6
1"
1!
#264
0!
#265
04
b1 2
b11 6
0"
1!
#266
0!
#267
15
b1 6
b11 2
1!
#268
0!
#269
1)
1&
05
b10 6
b1 0
b1010 .
b1 2
1!
#270
0!
#271
1/
b11 6
b10 2
1!
#272
0!
#273
b1111001 ,
b1111001 <
b1 -
b1 ;
b1 ?
b10000000000 >
15
0/
b100 6
b1010 3
b1010 =
b11 2
1!
#274
0!
#275
0)
11
05
b0 6
b0 0
b10100 .
b100 2
1!
#276
0!
#277
14
01
b0 2
b110 #
1!
#278
0!
#279
b1000000 ,
b1000000 <
b0 -
b0 ;
b0 ?
b0 >
0&
b0 3
b0 =
b10 0
b110 .
b1 6
1"
1!
#280
0!
#281
04
b1 2
b11 6
0"
1!
#282
0!
#283
15
b1 6
b11 2
1!
#284
0!
#285
1)
1&
05
b10 6
b1 0
b1100 .
b1 2
1!
#286
0!
#287
1/
b11 6
b10 2
1!
#288
0!
#289
b100100 +
b100100 B
b1111001 ,
b1111001 <
b10 '
b10 @
b10 A
b1 -
b1 ;
b1 ?
b10010000000 >
15
0/
b100 6
b1100 3
b1100 =
b11 2
1!
#290
0!
#291
0)
11
05
b0 6
b0 0
b11000 .
b100 2
1!
#292
0!
#293
14
01
b0 2
b111 #
1!
#294
0!
#295
b1000000 +
b1000000 B
b1000000 ,
b1000000 <
b0 '
b0 @
b0 A
b0 -
b0 ;
b0 ?
b0 >
0&
b0 3
b0 =
b10 0
b111 .
b1 6
1"
1!
#296
0!
#297
04
b1 2
b11 6
0"
1!
#298
0!
#299
15
b1 6
b11 2
1!
#300
0!
#301
1)
1&
05
b10 6
b1 0
b1110 .
b1 2
1!
#302
0!
#303
1/
b11 6
b10 2
1!
#304
0!
#305
b11001 +
b11001 B
b1111001 ,
b1111001 <
b100 '
b100 @
b100 A
b1 -
b1 ;
b1 ?
b10100000000 >
15
0/
b100 6
b1110 3
b1110 =
b11 2
1!
#306
0!
#307
0)
11
05
b0 6
b0 0
b11100 .
b100 2
1!
#308
0!
#309
14
01
b0 2
b0 #
b11 $
1!
#310
0!
#311
b1000000 +
b1000000 B
b1000000 ,
b1000000 <
b0 '
b0 @
b0 A
b0 -
b0 ;
b0 ?
b0 >
1)
0&
b0 3
b0 =
b11 0
b0 .
b1 6
1"
1!
#312
0!
#313
04
b1 2
b10 6
0"
1!
#314
0!
#315
1/
b11 6
b10 2
1!
#316
0!
#317
15
0/
b1 6
b11 2
1!
#318
0!
#319
1&
05
b10 6
b1 0
b1 2
1!
#320
0!
#321
1/
b11 6
b10 2
1!
#322
0!
#323
15
0/
b100 6
b11 2
1!
#324
0!
#325
0)
11
05
b0 6
b0 0
b100 2
1!
#326
0!
#327
14
01
b0 2
b1 #
1!
#328
0!
#329
1)
0&
b11 0
b1 .
b1 6
1"
1!
#330
0!
#331
04
b1 2
b10 6
0"
1!
#332
0!
#333
1/
b11 6
b10 2
1!
#334
0!
#335
b1111001 +
b1111001 B
b1 '
b1 @
b1 A
b1000000 >
15
0/
b1 6
b1 3
b1 =
b11 2
1!
#336
0!
#337
1&
05
b10 6
b1 0
b10 .
b1 2
1!
#338
0!
#339
1/
b11 6
b10 2
1!
#340
0!
#341
b110000 +
b110000 B
b11 '
b11 @
b11 A
b11000000 >
15
0/
b100 6
b11 3
b11 =
b11 2
1!
#342
0!
#343
0)
11
05
b0 6
b0 0
b100 .
b100 2
1!
#344
0!
#345
14
01
b0 2
b10 #
1!
#346
0!
#347
b1000000 +
b1000000 B
b0 '
b0 @
b0 A
b0 >
1)
0&
b0 3
b0 =
b11 0
b10 .
b1 6
1"
1!
#348
0!
#349
04
b1 2
b10 6
0"
1!
#350
0!
#351
1/
b11 6
b10 2
1!
#352
0!
#353
b100100 +
b100100 B
b10 '
b10 @
b10 A
b10000000 >
15
0/
b1 6
b10 3
b10 =
b11 2
1!
#354
0!
#355
1&
05
b10 6
b1 0
b100 .
b1 2
1!
#356
0!
#357
1/
b11 6
b10 2
1!
#358
0!
#359
b10 +
b10 B
b110 '
b110 @
b110 A
b110000000 >
15
0/
b100 6
b110 3
b110 =
b11 2
1!
#360
0!
#361
0)
11
05
b0 6
b0 0
b1000 .
b100 2
1!
#362
0!
#363
14
01
b0 2
b11 #
1!
#364
0!
#365
b1000000 +
b1000000 B
b0 '
b0 @
b0 A
b0 >
1)
0&
b0 3
b0 =
b11 0
b11 .
b1 6
1"
1!
#366
0!
#367
04
b1 2
b10 6
0"
1!
#368
0!
#369
1/
b11 6
b10 2
1!
#370
0!
#371
b110000 +
b110000 B
b11 '
b11 @
b11 A
b11000000 >
15
0/
b1 6
b11 3
b11 =
b11 2
1!
#372
0!
#373
1&
05
b10 6
b1 0
b110 .
b1 2
1!
#374
0!
#375
1/
b11 6
b10 2
1!
#376
0!
#377
b10000 +
b10000 B
b1001 '
b1001 @
b1001 A
b1001000000 >
15
0/
b100 6
b1001 3
b1001 =
b11 2
1!
#378
0!
#379
0)
11
05
b0 6
b0 0
b1100 .
b100 2
1!
#380
0!
#381
14
01
b0 2
b100 #
1!
#382
0!
#383
b1000000 +
b1000000 B
b0 '
b0 @
b0 A
b0 >
1)
0&
b0 3
b0 =
b11 0
b100 .
b1 6
1"
1!
#384
0!
#385
04
b1 2
b10 6
0"
1!
#386
0!
#387
1/
b11 6
b10 2
1!
#388
0!
#389
b11001 +
b11001 B
b100 '
b100 @
b100 A
b100000000 >
15
0/
b1 6
b100 3
b100 =
b11 2
1!
#390
0!
#391
1&
05
b10 6
b1 0
b1000 .
b1 2
1!
#392
0!
#393
1/
b11 6
b10 2
1!
#394
0!
#395
b100100 +
b100100 B
b1111001 ,
b1111001 <
b10 '
b10 @
b10 A
b1 -
b1 ;
b1 ?
b10010000000 >
15
0/
b100 6
b1100 3
b1100 =
b11 2
1!
#396
0!
#397
0)
11
05
b0 6
b0 0
b10000 .
b100 2
1!
#398
0!
#399
14
01
b0 2
b101 #
1!
#400
0!
#401
b1000000 +
b1000000 B
b1000000 ,
b1000000 <
b0 '
b0 @
b0 A
b0 -
b0 ;
b0 ?
b0 >
1)
0&
b0 3
b0 =
b11 0
b101 .
b1 6
1"
1!
#402
0!
#403
04
b1 2
b10 6
0"
1!
#404
0!
#405
1/
b11 6
b10 2
1!
#406
0!
#407
b10010 +
b10010 B
b101 '
b101 @
b101 A
b101000000 >
15
0/
b1 6
b101 3
b101 =
b11 2
1!
#408
0!
#409
1&
05
b10 6
b1 0
b1010 .
b1 2
1!
#410
0!
#411
1/
b11 6
b10 2
1!
#412
0!
#413
b1111001 ,
b1111001 <
b1 -
b1 ;
b1 ?
b10101000000 >
15
0/
b100 6
b1111 3
b1111 =
b11 2
1!
#414
0!
#415
0)
11
05
b0 6
b0 0
b10100 .
b100 2
1!
#416
0!
#417
14
01
b0 2
b110 #
1!
#418
0!
#419
b1000000 +
b1000000 B
b1000000 ,
b1000000 <
b0 '
b0 @
b0 A
b0 -
b0 ;
b0 ?
b0 >
1)
0&
b0 3
b0 =
b11 0
b110 .
b1 6
1"
1!
#420
0!
#421
04
b1 2
b10 6
0"
1!
#422
0!
#423
1/
b11 6
b10 2
1!
#424
0!
#425
b10 +
b10 B
b110 '
b110 @
b110 A
b110000000 >
15
0/
b1 6
b110 3
b110 =
b11 2
1!
#426
0!
#427
1&
05
b10 6
b1 0
b1100 .
b1 2
1!
#428
0!
#429
1/
b11 6
b10 2
1!
#430
0!
#431
b0 +
b0 B
b1111001 ,
b1111001 <
b1000 '
b1000 @
b1000 A
b1 -
b1 ;
b1 ?
b11000000000 >
15
0/
b100 6
b10010 3
b10010 =
b11 2
1!
#432
0!
#433
0)
11
05
b0 6
b0 0
b11000 .
b100 2
1!
#434
0!
#435
14
01
b0 2
b111 #
1!
#436
0!
#437
b1000000 +
b1000000 B
b1000000 ,
b1000000 <
b0 '
b0 @
b0 A
b0 -
b0 ;
b0 ?
b0 >
1)
0&
b0 3
b0 =
b11 0
b111 .
b1 6
1"
1!
#438
0!
#439
04
b1 2
b10 6
0"
1!
#440
0!
#441
1/
b11 6
b10 2
1!
#442
0!
#443
b1111000 +
b1111000 B
b111 '
b111 @
b111 A
b111000000 >
15
0/
b1 6
b111 3
b111 =
b11 2
1!
#444
0!
#445
1&
05
b10 6
b1 0
b1110 .
b1 2
1!
#446
0!
#447
1/
b11 6
b10 2
1!
#448
0!
#449
b1111001 +
b1111001 B
b100100 ,
b100100 <
b1 '
b1 @
b1 A
b10 -
b10 ;
b10 ?
b100001000000 >
15
0/
b100 6
b10101 3
b10101 =
b11 2
1!
#450
0!
#451
0)
11
05
b0 6
b0 0
b11100 .
b100 2
1!
#452
0!
#453
14
01
b0 2
b0 #
b100 $
1!
#454
0!
#455
b1000000 +
b1000000 B
b1000000 ,
b1000000 <
b0 '
b0 @
b0 A
b0 -
b0 ;
b0 ?
b0 >
0&
b0 3
b0 =
b100 0
b0 .
b1 6
1"
1!
#456
0!
#457
04
b1 2
b11 6
0"
1!
#458
0!
#459
15
b1 6
b11 2
1!
#460
0!
#461
05
b11 6
b10 0
b1 2
1!
#462
0!
#463
15
b1 6
b11 2
1!
#464
0!
#465
1)
1&
05
b10 6
b1 0
b1 2
1!
#466
0!
#467
1/
b11 6
b10 2
1!
#468
0!
#469
15
0/
b100 6
b11 2
1!
#470
0!
#471
0)
11
05
b0 6
b0 0
b100 2
1!
#472
0!
#473
14
01
b0 2
b1 #
1!
#474
0!
#475
0&
b100 0
b1 .
b1 6
1"
1!
#476
0!
#477
04
b1 2
b11 6
0"
1!
#478
0!
#479
15
b1 6
b11 2
1!
#480
0!
#481
05
b11 6
b10 0
b10 .
b1 2
1!
#482
0!
#483
15
b1 6
b11 2
1!
#484
0!
#485
1)
1&
05
b10 6
b1 0
b100 .
b1 2
1!
#486
0!
#487
1/
b11 6
b10 2
1!
#488
0!
#489
b11001 +
b11001 B
b100 '
b100 @
b100 A
b100000000 >
15
0/
b100 6
b100 3
b100 =
b11 2
1!
#490
0!
#491
0)
11
05
b0 6
b0 0
b1000 .
b100 2
1!
#492
0!
#493
14
01
b0 2
b10 #
1!
#494
0!
#495
b1000000 +
b1000000 B
b0 '
b0 @
b0 A
b0 >
0&
b0 3
b0 =
b100 0
b10 .
b1 6
1"
1!
#496
0!
#497
04
b1 2
b11 6
0"
1!
#498
0!
#499
15
b1 6
b11 2
1!
#500
0!
#501
05
b11 6
b10 0
b100 .
b1 2
1!
#502
0!
#503
15
b1 6
b11 2
1!
#504
0!
#505
1)
1&
05
b10 6
b1 0
b1000 .
b1 2
1!
#506
0!
#507
1/
b11 6
b10 2
1!
#508
0!
#509
b0 +
b0 B
b1000 '
b1000 @
b1000 A
b1000000000 >
15
0/
b100 6
b1000 3
b1000 =
b11 2
1!
#510
0!
#511
0)
11
05
b0 6
b0 0
b10000 .
b100 2
1!
#512
0!
#513
14
01
b0 2
b11 #
1!
#514
0!
#515
b1000000 +
b1000000 B
b0 '
b0 @
b0 A
b0 >
0&
b0 3
b0 =
b100 0
b11 .
b1 6
1"
1!
#516
0!
